metis_data/__init__.py
metis_data/cloud_files.py
metis_data/config.py
metis_data/const.py
metis_data/job.py
metis_data/namespace.py
metis_data/repo/__init__.py
metis_data/repo/properties.py
metis_data/repo/reader_options.py
metis_data/repo/readers.py
metis_data/repo/spark_util.py
metis_data/repo/sql_builder.py
metis_data/repo/streamer_readers.py
metis_data/repo/streamer_writers.py
metis_data/repo/volume.py
metis_data/repo/writers.py
metis_data/runner/__init__.py
metis_data/runner/job_runner.py
metis_data/runner/simple_job.py
metis_data/runner/simple_streamer.py
metis_data/runner/value.py
metis_data/schema.py
metis_data/session.py
metis_data/streamer.py
metis_data/structure/__init__.py
metis_data/structure/schema_util.py
metis_data/structure/value.py
metis_data/structure/vocab_util.py
metis_data/table.py
metis_data/util/chronos.py
metis_data/util/dataklass.py
metis_data/util/error.py
metis_data/util/error_messages.py
metis_data/util/fn.py
metis_data/util/json_util.py
metis_data/util/logger.py
metis_data/util/mod.py
metis_data/util/monad.py
metis_data/util/singleton.py
metis_data/util/tracer.py
metis_data-0.6.16.dist-info/METADATA
metis_data-0.6.16.dist-info/WHEEL
metis_data-0.6.16.dist-info/RECORD
