Metadata-Version: 2.1
Name: metis-data
Version: 0.6.16
Summary: 
Author: Col Perks
Author-email: wild.fauve@gmail.com
Requires-Python: >=3.10,<4.0
Classifier: Programming Language :: Python :: 3
Classifier: Programming Language :: Python :: 3.10
Classifier: Programming Language :: Python :: 3.11
Classifier: Programming Language :: Python :: 3.12
Requires-Dist: isoduration (>=20.11.0,<21.0.0)
Requires-Dist: pendulum (>=3.0.0,<4.0.0)
Requires-Dist: pino (>=0.6.0,<0.7.0)
Requires-Dist: pymonad (>=2.4.0,<3.0.0)
